{
 "Song Details": "Rincian Lagu",
 "Language": "Bahasa",
 "Genre": "Genre",
 "Gender": "Jenis Kelamin",
 "Musical Instrument": "Alat Musik",
 "Tempo": "Tempo",
 "Detail": "Rincian",
 "Creation Date": "Tanggal Pembuatan",
 "Song Length": "Durasi Lagu",
 "Artist": "Artis",
 "Lyrics": "Lirik",
 "NFT Status": "Status NFT",
 "Buy NFT": "Beli NFT",
 "Release": "Rilis",
 "Mint": "Mint",
 "Sell": "Jual",
 "Cancel": "Batalkan",
 "AI Lyrics & Songwriting": "Lirik & Penulisan Lagu AI",
 "AI Singing Evaluation": "Evaluasi Bernyanyi AI",
 "AI Cover Creation": "Pembuatan Cover AI",
 "Type": "Jenis",
 "Copy Link": "Salin Tautan",
 "Download": "Unduh",
 "TXIDs": "TXID",
 "Comments": "Komentar",
 "Write a comment": "Tulis komentar",
 "Post": "Kirim",
 "seconds ago": "beberapa detik yang lalu",
 "Reply": "Balas",
 "edit": "edit",
 "delete": "hapus",
 "Are you sure?": "Apakah kamu yakin?",
 "Once you delete this comment it will be gone forever.": "Setelah komentar ini dihapus, tidak bisa dikembalikan.",
 "Delete": "Hapus",
 "Type your reply here": "Ketik balasanmu di sini",
 "No comments here.": "Belum ada komentar.",
 "Be the first one to comment!": "Jadilah yang pertama untuk berkomentar!",
 "Songs Leaderboard Rank": "Peringkat Papan Skor Lagu",
 "Most Plays": "Paling Banyak Diputar",
 "Song Title": "Judul Lagu",
 "Plays": "Jumlah Putar",
 "Likes": "Suka",
 "Details": "Rincian",
 "Introduction": "Perkenalan",
 "Your Picks": "Pilihanmu",
 "Top tracks from your favorite genre.": "Lagu-lagu teratas dari genre favoritmu.",
 "Similar Vibes": "Getaran Serupa",
 "Top tracks from the same genre as this song.": "Lagu-lagu teratas dari genre yang sama dengan lagu ini."
}